epicure/__init__.py
epicure/demo.py
epicure/collection/__init__.py
epicure/collection/colors.py
epicure/file_handling/__init__.py
epicure/file_handling/json.py
epicure/input/__init__.py
epicure/input/question.py
epicure/output/__init__.py
epicure/output/print.py
epicure_utils-0.0.5.dist-info/LICENSE
epicure_utils-0.0.5.dist-info/METADATA
epicure_utils-0.0.5.dist-info/WHEEL
epicure_utils-0.0.5.dist-info/top_level.txt
epicure_utils-0.0.5.dist-info/RECORD
