Metadata-Version: 2.1
Name: epicure-utils
Version: 0.0.5
Summary: A common utils Python library. Don't write that one little function again!
Author-email: Patilla Code <patillacode@gmail.com>
License: GNU General Public License v3 (GPLv3)
Project-URL: homepage, https://github.com/patillacode/epicure
Project-URL: repository, https://github.com/patillacode/epicure
Keywords: utils,helpers
Classifier: Programming Language :: Python :: 3
Classifier: License :: OSI Approved :: GNU General Public License v3 (GPLv3)
Classifier: Operating System :: OS Independent
Requires-Python: >=3.10
License-File: LICENSE
Provides-Extra: test
Requires-Dist: alabaster==1.0.0; extra == "test"
Requires-Dist: asttokens==2.4.1; extra == "test"
Requires-Dist: babel==2.16.0; extra == "test"
Requires-Dist: backports-tarfile==1.2.0; extra == "test"
Requires-Dist: build==1.2.2.post1; extra == "test"
Requires-Dist: certifi==2024.8.30; extra == "test"
Requires-Dist: cfgv==3.4.0; extra == "test"
Requires-Dist: charset-normalizer==3.4.0; extra == "test"
Requires-Dist: click==8.1.7; extra == "test"
Requires-Dist: colorama==0.4.6; extra == "test"
Requires-Dist: distlib==0.3.9; extra == "test"
Requires-Dist: docutils==0.21.2; extra == "test"
Requires-Dist: executing==2.1.0; extra == "test"
Requires-Dist: filelock==3.16.1; extra == "test"
Requires-Dist: icecream==2.1.3; extra == "test"
Requires-Dist: identify==2.6.2; extra == "test"
Requires-Dist: idna==3.10; extra == "test"
Requires-Dist: imagesize==1.4.1; extra == "test"
Requires-Dist: importlib-metadata==8.5.0; extra == "test"
Requires-Dist: jaraco-classes==3.4.0; extra == "test"
Requires-Dist: jaraco-context==6.0.1; extra == "test"
Requires-Dist: jaraco-functools==4.1.0; extra == "test"
Requires-Dist: jinja2==3.1.4; extra == "test"
Requires-Dist: keyring==25.5.0; extra == "test"
Requires-Dist: markdown-it-py==3.0.0; extra == "test"
Requires-Dist: markupsafe==3.0.2; extra == "test"
Requires-Dist: mdurl==0.1.2; extra == "test"
Requires-Dist: more-itertools==10.5.0; extra == "test"
Requires-Dist: nh3==0.2.18; extra == "test"
Requires-Dist: nodeenv==1.9.1; extra == "test"
Requires-Dist: packaging==24.2; extra == "test"
Requires-Dist: pip-tools==7.4.1; extra == "test"
Requires-Dist: pkginfo==1.10.0; extra == "test"
Requires-Dist: platformdirs==4.3.6; extra == "test"
Requires-Dist: pre-commit==4.0.1; extra == "test"
Requires-Dist: pybadges==3.0.1; extra == "test"
Requires-Dist: pygments==2.18.0; extra == "test"
Requires-Dist: pyproject-hooks==1.2.0; extra == "test"
Requires-Dist: python-dotenv==1.0.1; extra == "test"
Requires-Dist: pyyaml==6.0.2; extra == "test"
Requires-Dist: readme-renderer==44.0; extra == "test"
Requires-Dist: requests==2.32.3; extra == "test"
Requires-Dist: requests-toolbelt==1.0.0; extra == "test"
Requires-Dist: rfc3986==2.0.0; extra == "test"
Requires-Dist: rich==13.9.4; extra == "test"
Requires-Dist: six==1.16.0; extra == "test"
Requires-Dist: snowballstemmer==2.2.0; extra == "test"
Requires-Dist: sphinx==8.1.3; extra == "test"
Requires-Dist: sphinx-autodoc-typehints==2.5.0; extra == "test"
Requires-Dist: sphinx-rtd-theme==3.0.2; extra == "test"
Requires-Dist: sphinxcontrib-applehelp==2.0.0; extra == "test"
Requires-Dist: sphinxcontrib-devhelp==2.0.0; extra == "test"
Requires-Dist: sphinxcontrib-htmlhelp==2.1.0; extra == "test"
Requires-Dist: sphinxcontrib-jquery==4.1; extra == "test"
Requires-Dist: sphinxcontrib-jsmath==1.0.1; extra == "test"
Requires-Dist: sphinxcontrib-qthelp==2.0.0; extra == "test"
Requires-Dist: sphinxcontrib-serializinghtml==2.0.0; extra == "test"
Requires-Dist: twine==5.1.1; extra == "test"
Requires-Dist: urllib3==2.2.3; extra == "test"
Requires-Dist: virtualenv==20.27.1; extra == "test"
Requires-Dist: wheel==0.45.0; extra == "test"
Requires-Dist: zipp==3.21.0; extra == "test"
Requires-Dist: alabaster==1.0.0; extra == "test"
Requires-Dist: asttokens==2.4.1; extra == "test"
Requires-Dist: babel==2.16.0; extra == "test"
Requires-Dist: backports-tarfile==1.2.0; extra == "test"
Requires-Dist: build==1.2.2.post1; extra == "test"
Requires-Dist: certifi==2024.8.30; extra == "test"
Requires-Dist: cfgv==3.4.0; extra == "test"
Requires-Dist: charset-normalizer==3.4.0; extra == "test"
Requires-Dist: click==8.1.7; extra == "test"
Requires-Dist: colorama==0.4.6; extra == "test"
Requires-Dist: coverage==7.6.7; extra == "test"
Requires-Dist: distlib==0.3.9; extra == "test"
Requires-Dist: docutils==0.21.2; extra == "test"
Requires-Dist: executing==2.1.0; extra == "test"
Requires-Dist: filelock==3.16.1; extra == "test"
Requires-Dist: icecream==2.1.3; extra == "test"
Requires-Dist: identify==2.6.2; extra == "test"
Requires-Dist: idna==3.10; extra == "test"
Requires-Dist: imagesize==1.4.1; extra == "test"
Requires-Dist: importlib-metadata==8.5.0; extra == "test"
Requires-Dist: iniconfig==2.0.0; extra == "test"
Requires-Dist: jaraco-classes==3.4.0; extra == "test"
Requires-Dist: jaraco-context==6.0.1; extra == "test"
Requires-Dist: jaraco-functools==4.1.0; extra == "test"
Requires-Dist: jinja2==3.1.4; extra == "test"
Requires-Dist: keyring==25.5.0; extra == "test"
Requires-Dist: markdown-it-py==3.0.0; extra == "test"
Requires-Dist: markupsafe==3.0.2; extra == "test"
Requires-Dist: mdurl==0.1.2; extra == "test"
Requires-Dist: more-itertools==10.5.0; extra == "test"
Requires-Dist: nh3==0.2.18; extra == "test"
Requires-Dist: nodeenv==1.9.1; extra == "test"
Requires-Dist: packaging==24.2; extra == "test"
Requires-Dist: pip-tools==7.4.1; extra == "test"
Requires-Dist: pkginfo==1.10.0; extra == "test"
Requires-Dist: platformdirs==4.3.6; extra == "test"
Requires-Dist: pluggy==1.5.0; extra == "test"
Requires-Dist: pre-commit==4.0.1; extra == "test"
Requires-Dist: pybadges==3.0.1; extra == "test"
Requires-Dist: pygments==2.18.0; extra == "test"
Requires-Dist: pyproject-hooks==1.2.0; extra == "test"
Requires-Dist: pytest==8.3.3; extra == "test"
Requires-Dist: pytest-click==1.1.0; extra == "test"
Requires-Dist: pytest-mock==3.14.0; extra == "test"
Requires-Dist: python-dotenv==1.0.1; extra == "test"
Requires-Dist: pyyaml==6.0.2; extra == "test"
Requires-Dist: readme-renderer==44.0; extra == "test"
Requires-Dist: requests==2.32.3; extra == "test"
Requires-Dist: requests-toolbelt==1.0.0; extra == "test"
Requires-Dist: rfc3986==2.0.0; extra == "test"
Requires-Dist: rich==13.9.4; extra == "test"
Requires-Dist: six==1.16.0; extra == "test"
Requires-Dist: snowballstemmer==2.2.0; extra == "test"
Requires-Dist: sphinx==8.1.3; extra == "test"
Requires-Dist: sphinx-autodoc-typehints==2.5.0; extra == "test"
Requires-Dist: sphinx-rtd-theme==3.0.2; extra == "test"
Requires-Dist: sphinxcontrib-applehelp==2.0.0; extra == "test"
Requires-Dist: sphinxcontrib-devhelp==2.0.0; extra == "test"
Requires-Dist: sphinxcontrib-htmlhelp==2.1.0; extra == "test"
Requires-Dist: sphinxcontrib-jquery==4.1; extra == "test"
Requires-Dist: sphinxcontrib-jsmath==1.0.1; extra == "test"
Requires-Dist: sphinxcontrib-qthelp==2.0.0; extra == "test"
Requires-Dist: sphinxcontrib-serializinghtml==2.0.0; extra == "test"
Requires-Dist: twine==5.1.1; extra == "test"
Requires-Dist: urllib3==2.2.3; extra == "test"
Requires-Dist: virtualenv==20.27.1; extra == "test"
Requires-Dist: wheel==0.45.0; extra == "test"
Requires-Dist: zipp==3.21.0; extra == "test"
